pyright_to_gitlab.py
pyright_to_gitlab-1.1.0.dist-info/METADATA
pyright_to_gitlab-1.1.0.dist-info/WHEEL
pyright_to_gitlab-1.1.0.dist-info/entry_points.txt
pyright_to_gitlab-1.1.0.dist-info/licenses/LICENSE
pyright_to_gitlab-1.1.0.dist-info/RECORD
