Metadata-Version: 2.4
Name: pyright-to-gitlab
Version: 1.1.0
Summary: Convert Pyright JSON output to GitLab CI/CD format
Project-URL: homepage, https://github.com/schollm/pyright-to-gitlab/
Project-URL: repository, https://github.com/schollm/pyright-to-gitlab/
Project-URL: pypi, https://pypi.org/project/pyright-to-gitlab
Author: Micha Schöll
License-Expression: MIT
License-File: LICENSE
Keywords: ci/cd,gitlab,pyright
Classifier: Development Status :: 5 - Production/Stable
Classifier: Intended Audience :: Developers
Classifier: License :: OSI Approved :: MIT License
Classifier: Programming Language :: Python :: 3.7
Classifier: Programming Language :: Python :: 3.8
Classifier: Programming Language :: Python :: 3.9
Classifier: Programming Language :: Python :: 3.10
Classifier: Programming Language :: Python :: 3.11
Classifier: Programming Language :: Python :: 3.12
Classifier: Programming Language :: Python :: 3.13
Classifier: Programming Language :: Python :: 3.14
Classifier: Topic :: Software Development
Classifier: Topic :: Software Development :: Testing
Classifier: Topic :: Utilities
Classifier: Typing :: Typed
Requires-Python: >=3.6
